zbq/__init__.py
zbq/base.py
zbq/main.py
zbq/main.py.tmp.1407.1755088447066
zbq/main.py.tmp.1407.1755088450880
zbq/storage.py
zbq-0.2.9.dist-info/METADATA
zbq-0.2.9.dist-info/WHEEL
zbq-0.2.9.dist-info/entry_points.txt
zbq-0.2.9.dist-info/RECORD
