Metadata-Version: 2.4
Name: zbq
Version: 0.2.9
Summary: A lightweight, wrapper around Google Cloud BigQuery with Polars integration. Simplifies querying and data ingestion with a unified interface, supporting read, write, insert, and delete operations on BigQuery tables.
Author-email: FrocketGaming <frocketgames@gmail.com>
Requires-Python: >=3.11
Requires-Dist: google-cloud-bigquery-storage>=2.32.0
Requires-Dist: google-cloud-bigquery>=3.34.0
Requires-Dist: google-cloud-storage>=3.1.1
Requires-Dist: loguru>=0.7.0
Requires-Dist: polars>=1.31.0
Requires-Dist: pyarrow>=21.0.0
Requires-Dist: tqdm>=4.67.1
